pyreact_start/__init__.py
pyreact_start/cli.py
pyreact_start/inertia.py
pyreact_start/js/src/cli.ts
pyreact_start-0.1.0.dist-info/WHEEL
pyreact_start-0.1.0.dist-info/entry_points.txt
pyreact_start-0.1.0.dist-info/METADATA
pyreact_start-0.1.0.dist-info/RECORD
