Metadata-Version: 2.4
Name: pyreact-start
Version: 0.1.0
Summary: Full-stack React + Python with zero configuration. Build modern React apps with FastAPI, Bun, Inertia.js, and Tailwind CSS.
Keywords: react,fastapi,bun,inertia,tailwind,ssr,full-stack
License-Expression: MIT
Classifier: Development Status :: 4 - Beta
Classifier: Framework :: FastAPI
Classifier: Intended Audience :: Developers
Classifier: License :: OSI Approved :: MIT License
Classifier: Programming Language :: Python :: 3.11
Classifier: Programming Language :: Python :: 3.12
Classifier: Topic :: Internet :: WWW/HTTP :: HTTP Servers
Requires-Dist: fastapi>=0.115.8
Requires-Dist: httpx>=0.27.0
Requires-Python: >=3.11
Project-URL: Homepage, https://github.com/kjrjay/pyreact-start
Project-URL: Repository, https://github.com/kjrjay/pyreact-start
